minchin/jrnl/contrib/exporter/obsidian.py
minchin.jrnl.contrib.exporter.obsidian-1.0.0.dist-info/LICENSE
minchin.jrnl.contrib.exporter.obsidian-1.0.0.dist-info/METADATA
minchin.jrnl.contrib.exporter.obsidian-1.0.0.dist-info/WHEEL
minchin.jrnl.contrib.exporter.obsidian-1.0.0.dist-info/top_level.txt
minchin.jrnl.contrib.exporter.obsidian-1.0.0.dist-info/RECORD
