Metadata-Version: 2.1
Name: minchin.jrnl.contrib.exporter.obsidian
Version: 1.0.0
Summary: Obsidian Custom Exporter for `minchin.jrnl`
Author-email: William Minchin <w_minchin@hotmail.com>
Maintainer-email: William Minchin <w_minchin@hotmail.com>
License: MIT
Project-URL: Homepage, http://minchin.ca/minchin.jrnl/
Project-URL: Bug Tracker, https://github.com/MinchinWeb/minchin.jrnl.contrib.exporter.obsidian/issues
Project-URL: Repository, https://github.com/MinchinWeb/minchin.jrnl.contrib.exporter.obsidian
License-File: LICENSE
Requires-Dist: minchin.jrnl >=7.1
Provides-Extra: dev
Requires-Dist: pip-tools >=7 ; extra == 'dev'
Requires-Dist: black ; extra == 'dev'
Requires-Dist: isort ; extra == 'dev'
Requires-Dist: minchin.releaser ; extra == 'dev'
